netbox_workload_manager/__init__.py
netbox_workload_manager/filtersets.py
netbox_workload_manager/navigation.py
netbox_workload_manager/tables.py
netbox_workload_manager/urls.py
netbox_workload_manager/api/__init__.py
netbox_workload_manager/api/serializers.py
netbox_workload_manager/api/urls.py
netbox_workload_manager/api/views.py
netbox_workload_manager/forms/__init__.py
netbox_workload_manager/forms/workload_cluster.py
netbox_workload_manager/forms/workload_cluster_type.py
netbox_workload_manager/forms/workload_service.py
netbox_workload_manager/migrations/0001_initial.py
netbox_workload_manager/migrations/0002_workloadservice_workload_cluster.py
netbox_workload_manager/migrations/__init__.py
netbox_workload_manager/models/__init__.py
netbox_workload_manager/models/workload_cluster.py
netbox_workload_manager/models/workload_cluster_type.py
netbox_workload_manager/models/workload_service.py
netbox_workload_manager/templates/netbox_workload_manager/workloadcluster.html
netbox_workload_manager/templates/netbox_workload_manager/workloadclustertype.html
netbox_workload_manager/templates/netbox_workload_manager/workloadservice.html
netbox_workload_manager/templates/netbox_workload_manager/generic/bulk_remove.html
netbox_workload_manager/templates/netbox_workload_manager/viewtab_contact/workloadcluster_contact.html
netbox_workload_manager/views/__init__.py
netbox_workload_manager/views/workload_cluster.py
netbox_workload_manager/views/workload_cluster_type.py
netbox_workload_manager/views/workload_service.py
netbox_workload_manager-1.1.1.dist-info/LICENSE
netbox_workload_manager-1.1.1.dist-info/METADATA
netbox_workload_manager-1.1.1.dist-info/WHEEL
netbox_workload_manager-1.1.1.dist-info/top_level.txt
netbox_workload_manager-1.1.1.dist-info/RECORD
